{"id": "readfile", "path": "c:\\Users\\KEN\\Documents\\GitHub\\my_project\\Python\\FileIO\\readfile\\readfile.py", "mtime": 1612592563, "size": 92, "hash": "918d1b0d46b6bbdd50bacfde1f99ad7366c3e6217a62ef249f91d76f251587f9", "data_mtime": 1612592124, "dependencies": ["builtins", "_typeshed", "abc", "io", "typing"], "suppressed": [], "options": {"strict_equality": false, "follow_imports": "silent", "disallow_untyped_decorators": false, "implicit_reexport": true, "no_implicit_optional": false, "bazel": false, "follow_imports_for_stubs": false, "disallow_incomplete_defs": false, "disallow_untyped_calls": false, "ignore_missing_imports": true, "disallow_untyped_defs": false, "disallow_any_explicit": false, "warn_return_any": false, "disallow_any_decorated": false, "check_untyped_defs": false, "warn_unreachable": false, "disallow_subclassing_any": false, "allow_redefinition": false, "warn_unused_ignores": false, "allow_untyped_globals": false, "local_partial_types": false, "strict_optional": true, "always_true": [], "warn_no_return": true, "disallow_any_generics": false, "show_none_errors": true, "mypyc": false, "disallow_any_unimported": false, "strict_optional_whitelist": null, "disallow_any_expr": false, "always_false": [], "platform": "win32", "ignore_errors": false, "plugins": []}, "dep_prios": [5, 30, 30, 30, 30], "dep_lines": [1, 1, 1, 1, 1], "interface_hash": "3dfe5619c17ab634acabd3110d300dfbf4c3489618c45e7b386c9ac562a1c31b", "version_id": "0.800", "ignore_all": false, "plugin_data": null}